pyxnat/__init__.py
pyxnat/version.py
pyxnat/core/__init__.py
pyxnat/core/array.py
pyxnat/core/attributes.py
pyxnat/core/downloadutils.py
pyxnat/core/errors.py
pyxnat/core/help.py
pyxnat/core/httputil.py
pyxnat/core/interfaces.py
pyxnat/core/jsonutil.py
pyxnat/core/manage.py
pyxnat/core/pathutil.py
pyxnat/core/pipelines.py
pyxnat/core/provenance.py
pyxnat/core/resources.py
pyxnat/core/schema.py
pyxnat/core/search.py
pyxnat/core/select.py
pyxnat/core/tags.py
pyxnat/core/uriutil.py
pyxnat/core/users.py
pyxnat/core/xpass.py
pyxnat/core/xpath_store.py
pyxnat/core/derivatives/__init__.py
pyxnat/core/derivatives/ashs.py
pyxnat/tests/__init__.py
pyxnat/tests/array_test.py
pyxnat/tests/attributes_test.py
pyxnat/tests/custom_variables_test.py
pyxnat/tests/downloadutils_test.py
pyxnat/tests/experiments_test.py
pyxnat/tests/graphdata_test.py
pyxnat/tests/inspector_test.py
pyxnat/tests/interfaces_test.py
pyxnat/tests/jsonutil_test.py
pyxnat/tests/manage_test.py
pyxnat/tests/pathutil_test.py
pyxnat/tests/pipelines_test.py
pyxnat/tests/prearchive_test.py
pyxnat/tests/project_manager_test.py
pyxnat/tests/provenance_test.py
pyxnat/tests/repr_test.py
pyxnat/tests/resources_test.py
pyxnat/tests/scans_test.py
pyxnat/tests/search_test.py
pyxnat/tests/select_test.py
pyxnat/tests/sessionmirror_test.py
pyxnat/tests/test_resource_functions.py
pyxnat/tests/uriutil_test.py
pyxnat/tests/user_and_project_management_test.py
pyxnat/tests/xpass_test.py
pyxnat/tests/xpath_test.py
pyxnat-1.6.data/scripts/sessionmirror.py
pyxnat-1.6.dist-info/LICENSE
pyxnat-1.6.dist-info/METADATA
pyxnat-1.6.dist-info/WHEEL
pyxnat-1.6.dist-info/top_level.txt
pyxnat-1.6.dist-info/RECORD
