Metadata-Version: 2.1
Name: pyxnat
Version: 1.6
Summary: XNAT in Python
Home-page: https://github.com/pyxnat/pyxnat
Author: Yannick Schwartz
Author-email: yannick.schwartz@cea.fr
License: BSD
Platform: any
Classifier: Development Status :: 4 - Beta
Classifier: Environment :: Console
Classifier: Intended Audience :: Developers
Classifier: Intended Audience :: Science/Research
Classifier: Intended Audience :: Education
Classifier: License :: OSI Approved :: BSD License
Classifier: Operating System :: OS Independent
Classifier: Topic :: Scientific/Engineering
Classifier: Topic :: Utilities
Classifier: Topic :: Internet :: WWW/HTTP
Classifier: Programming Language :: Python :: 3.8
Classifier: Programming Language :: Python :: 3.9
